spqsigs/__init__.py
spqsigs-0.1.2.dist-info/LICENSE
spqsigs-0.1.2.dist-info/METADATA
spqsigs-0.1.2.dist-info/WHEEL
spqsigs-0.1.2.dist-info/top_level.txt
spqsigs-0.1.2.dist-info/RECORD
