Metadata-Version: 2.1
Name: spqsigs
Version: 0.1.2
Summary: Simple Post-Quantum Signature library
Home-page: https://github.com/pibara/pyspqsigs
Author: Rob J Meijer
Author-email: pibara@gmail.com
License: BSD
Keywords: signing postquantum blake2 merkletree wots
Platform: UNKNOWN
Classifier: Development Status :: 4 - Beta
Classifier: Intended Audience :: Developers
Classifier: Topic :: Software Development :: Libraries
Classifier: License :: OSI Approved :: BSD License
Classifier: Programming Language :: Python :: 3
Classifier: Programming Language :: Python :: 3.8
Classifier: Operating System :: OS Independent
Classifier: Environment :: Other Environment
Requires-Dist: bitstring
